nlweb_dataload/__init__.py
nlweb_dataload/config.py
nlweb_dataload/csv2schema.py
nlweb_dataload/db_load.py
nlweb_dataload/embedding.py
nlweb_dataload/rss2schema.py
nlweb_dataload/writer.py
nlweb_dataload-0.5.5.dist-info/METADATA
nlweb_dataload-0.5.5.dist-info/WHEEL
nlweb_dataload-0.5.5.dist-info/top_level.txt
nlweb_dataload-0.5.5.dist-info/RECORD
