Metadata-Version: 2.4
Name: nlweb-dataload
Version: 0.5.5
Summary: Data loading tools for NLWeb - load schema.org JSON and RSS feeds into vector databases
Author: Microsoft Corporation
License: MIT
Project-URL: Homepage, https://github.com/nlweb-ai/NLWeb_Core
Project-URL: Repository, https://github.com/nlweb-ai/NLWeb_Core
Classifier: Development Status :: 4 - Beta
Classifier: Intended Audience :: Developers
Classifier: License :: OSI Approved :: MIT License
Classifier: Programming Language :: Python :: 3
Classifier: Programming Language :: Python :: 3.8
Classifier: Programming Language :: Python :: 3.9
Classifier: Programming Language :: Python :: 3.10
Classifier: Programming Language :: Python :: 3.11
Classifier: Programming Language :: Python :: 3.12
Classifier: Topic :: Software Development :: Libraries :: Python Modules
Requires-Python: >=3.8
Requires-Dist: pyyaml>=6.0
Requires-Dist: feedparser>=6.0.0
Requires-Dist: aiohttp>=3.8.0
Provides-Extra: azure
Requires-Dist: openai>=1.12.0; extra == "azure"
Requires-Dist: azure-identity>=1.12.0; extra == "azure"
Provides-Extra: openai
Requires-Dist: openai>=1.12.0; extra == "openai"
Provides-Extra: dev
Requires-Dist: pytest>=7.0.0; extra == "dev"
Requires-Dist: pytest-asyncio>=0.21.0; extra == "dev"
